docs/source/conf.py
scikit_base-0.12.5.dist-info/licenses/LICENSE
skbase/__init__.py
skbase/_exceptions.py
skbase/_nopytest_tests.py
skbase/base/__init__.py
skbase/base/_base.py
skbase/base/_clone_base.py
skbase/base/_clone_plugins.py
skbase/base/_meta.py
skbase/base/_tagmanager.py
skbase/base/_pretty_printing/__init__.py
skbase/base/_pretty_printing/_object_html_repr.py
skbase/base/_pretty_printing/_pprint.py
skbase/base/_pretty_printing/tests/__init__.py
skbase/base/_pretty_printing/tests/test_pprint.py
skbase/lookup/__init__.py
skbase/lookup/_lookup.py
skbase/lookup/tests/__init__.py
skbase/lookup/tests/test_lookup.py
skbase/testing/__init__.py
skbase/testing/test_all_objects.py
skbase/testing/utils/__init__.py
skbase/testing/utils/_conditional_fixtures.py
skbase/testing/utils/inspect.py
skbase/tests/__init__.py
skbase/tests/conftest.py
skbase/tests/test_base.py
skbase/tests/test_baseestimator.py
skbase/tests/test_exceptions.py
skbase/tests/test_meta.py
skbase/tests/mock_package/__init__.py
skbase/tests/mock_package/test_mock_package.py
skbase/utils/__init__.py
skbase/utils/_check.py
skbase/utils/_iter.py
skbase/utils/_nested_iter.py
skbase/utils/_utils.py
skbase/utils/doctest_run.py
skbase/utils/random_state.py
skbase/utils/stderr_mute.py
skbase/utils/stdout_mute.py
skbase/utils/deep_equals/__init__.py
skbase/utils/deep_equals/_common.py
skbase/utils/deep_equals/_deep_equals.py
skbase/utils/dependencies/__init__.py
skbase/utils/dependencies/_dependencies.py
skbase/utils/dependencies/_import.py
skbase/utils/dependencies/tests/__init__.py
skbase/utils/dependencies/tests/test_check_dependencies.py
skbase/utils/tests/__init__.py
skbase/utils/tests/test_check.py
skbase/utils/tests/test_deep_equals.py
skbase/utils/tests/test_iter.py
skbase/utils/tests/test_nested_iter.py
skbase/utils/tests/test_random_state.py
skbase/utils/tests/test_std_mute.py
skbase/utils/tests/test_utils.py
skbase/validate/__init__.py
skbase/validate/_named_objects.py
skbase/validate/_types.py
skbase/validate/tests/__init__.py
scikit_base-0.12.5.dist-info/METADATA
scikit_base-0.12.5.dist-info/WHEEL
scikit_base-0.12.5.dist-info/top_level.txt
scikit_base-0.12.5.dist-info/zip-safe
scikit_base-0.12.5.dist-info/RECORD
